antigranular_enterprise/__init__.py
antigranular_enterprise/client.py
antigranular_enterprise/sql_client.py
antigranular_enterprise/agent_client/agent_client.py
antigranular_enterprise/config/config.py
antigranular_enterprise/magics/errors.py
antigranular_enterprise/magics/magics.py
antigranular_enterprise/models/__init__.py
antigranular_enterprise/models/models.py
antigranular_enterprise/utils/__init__.py
antigranular_enterprise/utils/error_print.py
antigranular_enterprise/utils/logger.py
antigranular_enterprise/utils/print_request_id.py
antigranular_enterprise/utils/token_utils.py
antigranular_enterprise-2.3.5.dist-info/METADATA
antigranular_enterprise-2.3.5.dist-info/WHEEL
antigranular_enterprise-2.3.5.dist-info/licenses/LICENSE
antigranular_enterprise-2.3.5.dist-info/RECORD
