Metadata-Version: 2.4
Name: antigranular_enterprise
Version: 2.3.5
Summary: Antigranular Enterprise is a robust, scalable version of the Antigranular platform. It combines the power of differential privacy, providing a secure environment for handling and unlocking the full potential of unseen data. With enhanced features and dedicated support, Antigranular Enterprise is the ideal solution for businesses seeking to leverage the power of data privacy and security.
Author-email: "Oblivious Software Pvt. Ltd." <support@oblivious.com>
License-File: LICENSE
Requires-Python: >=3.9
Requires-Dist: authlib>=1.6.0
Requires-Dist: ipython>=7.34.0
Requires-Dist: loguru>=0.7.0
Requires-Dist: numpy==2.0.2
Requires-Dist: pandas==2.2.2
Requires-Dist: psutil==5.9.5
Requires-Dist: pydantic==2.11.4
Requires-Dist: pyjwt>=2.8.0
Requires-Dist: pyyaml>=6.0.1
Requires-Dist: requests>=2.31.0
Provides-Extra: dev
Requires-Dist: nbclient<1.0.0,>=0.8.0; extra == 'dev'
Requires-Dist: nbformat<6.0.0,>=5.9.1; extra == 'dev'
Requires-Dist: pytest-cov<5.0.0,>=4.0.0; extra == 'dev'
Requires-Dist: pytest<8.0.0,>=7.2.2; extra == 'dev'
Provides-Extra: onnx
Requires-Dist: onnx==1.18.0; extra == 'onnx'
Provides-Extra: torch
Requires-Dist: torch<2.0.0,>=1.10.0; extra == 'torch'
